{"id":14880822,"mediaExerciseId":"6a0e52d6-41ff-4ff8-9ee2-6eec53e570f9","exerciseName":"27","chapterName":"3","chapterTitle":"Working with Financial Statements","groupId":612275,"groupTitle":"Questions and Problems","isPremium":true,"sectionName":null,"sectionTitle":null,"pageNumber":89,"solutions":[{"id":5975688,"modifiedOn":"2021-01-01T00:00:00.000000","steps":[{"columns":[{"text":"In this problem, we are required to construct the DuPont identity for Smolira Golf Corp.","images":{"latex":null,"additional":null},"hasInvalidKatex":false,"isTextOnly":true}],"isResult":false,"stepNumber":1},{"columns":[{"text":"Before we begin, let us first define DuPont Identity.\n\n**DuPont Identity** is an expression that shows the Return on Equity (ROE) of a company.\n\nThe formula is denoted as follows:\n$$\\begin{aligned}\n\\textbf{ROE}& =\n \\text{Profit Margin} \\times\\text{Asset Turnover} \\times \\text{Equity multiplier}\\\\\\\\\n\\end{aligned}$$\n","images":{"latex":{"large":{"height":66,"srcUrl":"https://d2nchlq0f2u6vy.cloudfront.net/22/01/07/eabd471843106ab6493ac02e89d01b39/32aa788556c2cf5b9705104a45666b97/lateximg_large.png","width":996},"regular":{"height":34,"srcUrl":"https://d2nchlq0f2u6vy.cloudfront.net/22/01/07/eabd471843106ab6493ac02e89d01b39/32aa788556c2cf5b9705104a45666b97/lateximg.png","width":498}},"additional":null},"hasInvalidKatex":false,"isTextOnly":false}],"isResult":false,"stepNumber":2},{"columns":[{"text":"First, we need to determine the profit margin ratio:\n\n**Profit margin ratio** is a financial ratio that shows the percentage of profit the company produces from its operations.\n\nThe formula is denoted as follows:\n$$\\begin{aligned}\n\\textbf{Profit margin\n}& = \\dfrac{\\text{Operating profit}} {\\text{Net sales}}\\\\ \\\\\n\\end{aligned}$$\n\n\n","images":{"latex":{"large":{"height":200,"srcUrl":"https://d2nchlq0f2u6vy.cloudfront.net/22/01/07/eabd471843106ab6493ac02e89d01b39/faf60c5e5c4d41c389bf97a354d1bb96/lateximg_large.png","width":996},"regular":{"height":102,"srcUrl":"https://d2nchlq0f2u6vy.cloudfront.net/22/01/07/eabd471843106ab6493ac02e89d01b39/faf60c5e5c4d41c389bf97a354d1bb96/lateximg.png","width":498}},"additional":null},"hasInvalidKatex":false,"isTextOnly":false}],"isResult":false,"stepNumber":3},{"columns":[{"text":"The profit margin ratio can be computed as follows:\n\n$$\\begin{aligned}\n\\textbf{Profit margin\n}& = \\dfrac{\\text{Operating profit}} {\\text{Net sales}}\\\\ \\\\\n& = \\frac{\\$62,235} {\\$506,454}\\\\ \\\\\n&= \\boxed{0.1229}\\\\ \\\\\n&= \\boxed{12.29\\%}\\\\\n\\end{aligned}$$\n\\\nAs can be seen, the profit margin ratio is 12.29%.\n\n\n","images":{"latex":{"large":{"height":230,"srcUrl":"https://d2nchlq0f2u6vy.cloudfront.net/22/01/01/eabd471843106ab6493ac02e89d01b39/f132f6a2616825b692384ed1c92e67aa/lateximg_large.png","width":998},"regular":{"height":117,"srcUrl":"https://d2nchlq0f2u6vy.cloudfront.net/22/01/01/eabd471843106ab6493ac02e89d01b39/f132f6a2616825b692384ed1c92e67aa/lateximg.png","width":500}},"additional":null},"hasInvalidKatex":false,"isTextOnly":false}],"isResult":false,"stepNumber":4},{"columns":[{"text":"Next is to determine the asset turnover:\n\n**Asset turnover** is a financial ratio that shows if the company is efficient in relation to its total assets in generating revenue or sales.\n\nThe formula is denoted as follows:\n$$\\begin{aligned}\n\\textbf{Asset Turnover}& =\n \\dfrac{\\text{Net Sales}} {\\text{Average Total Assets}}\\\\ \\\\\n\\end{aligned}$$\n","images":{"latex":{"large":{"height":503,"srcUrl":"https://d2nchlq0f2u6vy.cloudfront.net/22/01/01/eabd471843106ab6493ac02e89d01b39/05c51506023223b109cb430ddafdf5d4/lateximg_large.png","width":736},"regular":{"height":253,"srcUrl":"https://d2nchlq0f2u6vy.cloudfront.net/22/01/01/eabd471843106ab6493ac02e89d01b39/05c51506023223b109cb430ddafdf5d4/lateximg.png","width":368}},"additional":null},"hasInvalidKatex":false,"isTextOnly":false}],"isResult":false,"stepNumber":5},{"columns":[{"text":"The asset turnover can be computed as follows:\n\n$$\\begin{aligned}\n\\textbf{Asset Turnover}& =\n \\dfrac{\\text{Net Sales}} {\\text{Average Total Assets}}\\\\ \\\\\n& = \\frac{\\$506,454} {(\\$552,811 + \\$627,868) \\div 2}\\\\ \\\\\n&= \\boxed{0.58}\\\\ \\\\\n\\end{aligned}$$\n\\\nAs can be seen, the asset turnover is 0.58.","images":{"latex":{"large":{"height":236,"srcUrl":"https://d2nchlq0f2u6vy.cloudfront.net/22/01/01/eabd471843106ab6493ac02e89d01b39/66c24dd0a75ef78dcf7fb7f82ff63dac/lateximg_large.png","width":995},"regular":{"height":120,"srcUrl":"https://d2nchlq0f2u6vy.cloudfront.net/22/01/01/eabd471843106ab6493ac02e89d01b39/66c24dd0a75ef78dcf7fb7f82ff63dac/lateximg.png","width":497}},"additional":null},"hasInvalidKatex":false,"isTextOnly":false}],"isResult":false,"stepNumber":6},{"columns":[{"text":"Last is to determine the equity multiplier:\n\n**Equity multiplier** measures a portion of a company's assets that is financed by shareholders' equity.\n\nThe formula is denoted as follows:\n$$\\begin{aligned}\n\\textbf{Equity multiplier}& =\n \\dfrac{\\text{Total Assets}} {\\text{Total Shareholders' Equity}}\\\\ \\\\\n\\end{aligned}$$\n","images":{"latex":{"large":{"height":456,"srcUrl":"https://d2nchlq0f2u6vy.cloudfront.net/22/01/01/eabd471843106ab6493ac02e89d01b39/7de47f0573e9f8291c4f305d5d7f9f9b/lateximg_large.png","width":811},"regular":{"height":229,"srcUrl":"https://d2nchlq0f2u6vy.cloudfront.net/22/01/01/eabd471843106ab6493ac02e89d01b39/7de47f0573e9f8291c4f305d5d7f9f9b/lateximg.png","width":405}},"additional":null},"hasInvalidKatex":false,"isTextOnly":false}],"isResult":false,"stepNumber":7},{"columns":[{"text":"The equity multiplier can be computed as follows:\n\n$$\\begin{aligned}\n\\textbf{Equity multiplier}& =\n \\dfrac{\\text{Total Assets}} {\\text{Total Shareholders' Equity}}\\\\ \\\\\n& = \\frac{\\$627,868} {\\$399,452}\\\\ \\\\\n&= \\boxed{1.57}\\\\ \\\\\n\\end{aligned}$$\n\\\nAs can be seen, the equity multiplier is 1.57.","images":{"latex":{"large":{"height":236,"srcUrl":"https://d2nchlq0f2u6vy.cloudfront.net/22/01/01/eabd471843106ab6493ac02e89d01b39/c9997b9a7574919d804c720329df9f6a/lateximg_large.png","width":995},"regular":{"height":120,"srcUrl":"https://d2nchlq0f2u6vy.cloudfront.net/22/01/01/eabd471843106ab6493ac02e89d01b39/c9997b9a7574919d804c720329df9f6a/lateximg.png","width":498}},"additional":null},"hasInvalidKatex":false,"isTextOnly":false}],"isResult":false,"stepNumber":8},{"columns":[{"text":"Finally, to determine return on equity or ROE:\n\n$$\\begin{aligned}\n\\textbf{ROE}& =\n \\text{Profit Margin} \\times\\text{Asset Turnover} \\times \\text{Equity multiplier}\\\\\\\\\n&=12.29\\%\\times 0.58 \\times 1.57 \\\\\\\\\n&=0.1229 \\times 0.58 \\times 1.57 \\\\\\\\\n&=\\boxed{0.1119}\\\\\\\\\n&=\\boxed{11.19\\%}\\\\\n\\end{aligned}$$\n\\\nIn conclusion, the ROE is 11.19%.","images":{"latex":{"large":{"height":454,"srcUrl":"https://d2nchlq0f2u6vy.cloudfront.net/22/01/01/eabd471843106ab6493ac02e89d01b39/466b068ad1b60bad847ec962febf4031/lateximg_large.png","width":827},"regular":{"height":228,"srcUrl":"https://d2nchlq0f2u6vy.cloudfront.net/22/01/01/eabd471843106ab6493ac02e89d01b39/466b068ad1b60bad847ec962febf4031/lateximg.png","width":413}},"additional":null},"hasInvalidKatex":false,"isTextOnly":false}],"isResult":false,"stepNumber":9}],"rating":5,"solutionUuid":"31fc472d-e188-446e-ab7e-95491157ba4e","editorVersion":2,"answeredOn":null,"ratingCount":null,"solutionOrder":null,"totalSteps":9},{"id":5985708,"modifiedOn":"2021-01-01T00:00:00.000000","steps":[{"columns":[{"text":"In this item, we will do the DuPont identity for Smolira Golf Corporation.","images":{"latex":{"large":{"height":28,"srcUrl":"https://d2nchlq0f2u6vy.cloudfront.net/22/01/05/5fcd3971360699d0db846e10184a1a0e/4928c5276eac9f4611bc28da141e92c4/lateximg_large.png","width":987},"regular":{"height":15,"srcUrl":"https://d2nchlq0f2u6vy.cloudfront.net/22/01/05/5fcd3971360699d0db846e10184a1a0e/4928c5276eac9f4611bc28da141e92c4/lateximg.png","width":494}},"additional":null},"hasInvalidKatex":false,"isTextOnly":true}],"isResult":false,"stepNumber":1},{"columns":[{"text":"**DuPont identity** is a powerful tool in analyzing the firm’s performance because it expounds the basic definition of Return on equity (ROE) which focuses only on the relationship of Net income and total equity.\n\\\nUsing this, we can dig more into related ratios and examine them in detail to determine the possible specific reasons behind the resulting ROE.","images":{"latex":{"large":{"height":181,"srcUrl":"https://d2nchlq0f2u6vy.cloudfront.net/22/01/05/5fcd3971360699d0db846e10184a1a0e/bd4da9176d315e1e16f4caae5d8c72c2/lateximg_large.png","width":997},"regular":{"height":91,"srcUrl":"https://d2nchlq0f2u6vy.cloudfront.net/22/01/05/5fcd3971360699d0db846e10184a1a0e/bd4da9176d315e1e16f4caae5d8c72c2/lateximg.png","width":499}},"additional":null},"hasInvalidKatex":false,"isTextOnly":false}],"isResult":false,"stepNumber":2},{"columns":[{"text":"The listed given are from the preceding item.\n|Given |Amount | \n|--|--:| \n| Profit margin |0.1229\n|Total asset turnover |0.86|\n|Equity multiplier |1.58|\n|Return on equity |16.81|","images":{"latex":{"large":{"height":103,"srcUrl":"https://d2nchlq0f2u6vy.cloudfront.net/22/01/05/5fcd3971360699d0db846e10184a1a0e/90157b7d1f8944bf88b692c8ab49b398/lateximg_large.png","width":1016},"regular":{"height":53,"srcUrl":"https://d2nchlq0f2u6vy.cloudfront.net/22/01/05/5fcd3971360699d0db846e10184a1a0e/90157b7d1f8944bf88b692c8ab49b398/lateximg.png","width":509}},"additional":null},"hasInvalidKatex":false,"isTextOnly":false}],"isResult":false,"stepNumber":3},{"columns":[{"text":"DuPont identity is expressed as follows:\n$$\\begin{aligned}\n\\text{ROE}&=\\text{Profit Margin x Total asset turnover x E.M.}\\\\\n\\end{aligned}$$\n\\\nwhere:\nEM= Equity Multiplier\n\\\nWe can say that **operating efficiency**, **asset use efficiency**, and **financial leverage** has an effect on the return on equity of a company.","images":{"latex":{"large":{"height":239,"srcUrl":"https://d2nchlq0f2u6vy.cloudfront.net/22/01/05/5fcd3971360699d0db846e10184a1a0e/0bbd1d5b6a90dca820351eaf525dc417/lateximg_large.png","width":997},"regular":{"height":121,"srcUrl":"https://d2nchlq0f2u6vy.cloudfront.net/22/01/05/5fcd3971360699d0db846e10184a1a0e/0bbd1d5b6a90dca820351eaf525dc417/lateximg.png","width":499}},"additional":null},"hasInvalidKatex":false,"isTextOnly":false}],"isResult":false,"stepNumber":4},{"columns":[{"text":"To solve for the ROE of Smolira using the DuPont entity, the computation will be as follows:\n$$\\begin{aligned}\n\\text{ROE}&=\\text{Profit Margin x Total asset turnover x E.M.}\\\\\n&=\\text{0.1229 x 0.86 x 1.58}\\\\\n&=\\boxed{\\textbf{0.1670 or 16.70\\%}}\\\\\n\\end{aligned}$$\n\\\nwhere:\nEM= Equity Multiplier\n\\\nFrom the previous exercise, we got 16.81% as ROE but **using the DuPont identity we got 16.70%** The slight difference is due to the rounding off but they are still the same.","images":{"latex":null,"additional":null},"hasInvalidKatex":false,"isTextOnly":false}],"isResult":false,"stepNumber":5}],"rating":5,"solutionUuid":"5d38ed59-bc9f-401a-a292-0bd615bc6bda","editorVersion":2,"answeredOn":null,"ratingCount":null,"solutionOrder":null,"totalSteps":5}],"textbook":{"authors":"Bradford D. Jordan, Randolph W. Westerfield, Stephen A. Ross","imageUrl":"https://d2nchlq0f2u6vy.cloudfront.net/textbook_covers/tmpm0p82b7h","imageThumbnailUrl":"https://d2nchlq0f2u6vy.cloudfront.net/cache/d1/d3/d1d34d106dd29dd2e71be582412ef59d.jpg","id":34320,"isbn":"9781259918957","isPremium":true,"title":"Fundamentals of Corporate Finance","edition":"12th Edition","verifiedSolutionCount":1217,"shouldBeIndexableForSeo":true,"modified":1665448474394,"active":true,"publisher":"McGraw-Hill Education","mainTextbookIsbn":null,"subjects":{"level1":["Social Science"],"level2":["Economics"],"level3":["Finance"]}},"nextExercises":[{"id":14880823,"exerciseName":"28","page":89,"hasSolution":true,"mediaExerciseId":"a0b08a3e-e423-449c-81be-4077bd43d088","_webUrl":"https://quizlet.com/explanations/textbook-solutions/fundamentals-of-corporate-finance-12th-edition-9781259918957/chapter-3-questions-and-problems-28-a0b08a3e-e423-449c-81be-4077bd43d088"},{"id":14880824,"exerciseName":"29","page":89,"hasSolution":true,"mediaExerciseId":"2e7dcaef-07e8-4940-a872-7d39fff2cdc9","_webUrl":"https://quizlet.com/explanations/textbook-solutions/fundamentals-of-corporate-finance-12th-edition-9781259918957/chapter-3-questions-and-problems-29-2e7dcaef-07e8-4940-a872-7d39fff2cdc9"}],"previousExercises":[{"id":14880821,"exerciseName":"26","page":88,"hasSolution":true,"mediaExerciseId":"034023d8-8c19-474f-b81e-0534d4d3999d","_webUrl":"https://quizlet.com/explanations/textbook-solutions/fundamentals-of-corporate-finance-12th-edition-9781259918957/chapter-3-questions-and-problems-26-034023d8-8c19-474f-b81e-0534d4d3999d"},{"id":14880820,"exerciseName":"25","page":87,"hasSolution":true,"mediaExerciseId":"c645beda-e0ee-4d82-9c16-b9190416397b","_webUrl":"https://quizlet.com/explanations/textbook-solutions/fundamentals-of-corporate-finance-12th-edition-9781259918957/chapter-3-questions-and-problems-25-c645beda-e0ee-4d82-9c16-b9190416397b"}],"_webUrl":"https://quizlet.com/explanations/textbook-solutions/fundamentals-of-corporate-finance-12th-edition-9781259918957/chapter-3-questions-and-problems-27-6a0e52d6-41ff-4ff8-9ee2-6eec53e570f9"}